diracx/core/__init__.py
diracx/core/exceptions.py
diracx/core/extensions.py
diracx/core/models.py
diracx/core/preferences.py
diracx/core/properties.py
diracx/core/py.typed
diracx/core/resources.py
diracx/core/s3.py
diracx/core/settings.py
diracx/core/utils.py
diracx/core/config/__init__.py
diracx/core/config/schema.py
diracx/core/config/sources.py
diracx_core-0.0.7.dist-info/METADATA
diracx_core-0.0.7.dist-info/WHEEL
diracx_core-0.0.7.dist-info/entry_points.txt
diracx_core-0.0.7.dist-info/RECORD
